transformer_smaller_training_vocab/__init__.py
transformer_smaller_training_vocab/contextual_reduce.py
transformer_smaller_training_vocab/logging_utils.py
transformer_smaller_training_vocab/modify_model.py
transformer_smaller_training_vocab/modify_tokenizer.py
transformer_smaller_training_vocab/py.typed
transformer_smaller_training_vocab/token_stats.py
transformer_smaller_training_vocab/transformer_set_vocab/__init__.py
transformer_smaller_training_vocab/transformer_set_vocab/auto_set_vocab.py
transformer_smaller_training_vocab/transformer_set_vocab/set_vocab_bert.py
transformer_smaller_training_vocab/transformer_set_vocab/set_vocab_fast_tokenizer.py
transformer_smaller_training_vocab/transformer_set_vocab/set_vocab_roberta.py
transformer_smaller_training_vocab/transformer_set_vocab/set_vocab_xlm_roberta.py
transformer_smaller_training_vocab/utils.py
transformer_smaller_training_vocab-0.4.1.dist-info/LICENSE
transformer_smaller_training_vocab-0.4.1.dist-info/METADATA
transformer_smaller_training_vocab-0.4.1.dist-info/WHEEL
transformer_smaller_training_vocab-0.4.1.dist-info/RECORD
