Metadata-Version: 2.3
Name: transformer-smaller-training-vocab
Version: 0.4.1
Summary: Temporary remove unused tokens during training to save ram and speed.
License: MIT
Author: Benedikt Fuchs
Author-email: benedikt.fuchs.staw@hotmail.com
Requires-Python: >=3.9,<4.0
Classifier: License :: OSI Approved :: MIT License
Classifier: Programming Language :: Python :: 3
Classifier: Programming Language :: Python :: 3.9
Classifier: Programming Language :: Python :: 3.10
Classifier: Programming Language :: Python :: 3.11
Classifier: Programming Language :: Python :: 3.12
Classifier: Programming Language :: Python :: 3.13
Requires-Dist: torch (>=1.8.0,<3.0.0,!=2.0.1)
Requires-Dist: transformers[sentencepiece,torch] (>=4.1,<5.0)
Project-URL: Repository, https://github.com/helpmefindaname/transformer-smaller-training-vocab
